fluentcms_publishing/__init__.py
fluentcms_publishing/admin.py
fluentcms_publishing/apps.py
fluentcms_publishing/compat.py
fluentcms_publishing/managers.py
fluentcms_publishing/middleware.py
fluentcms_publishing/models.py
fluentcms_publishing/monkey_patches.py
fluentcms_publishing/signals.py
fluentcms_publishing/utils.py
fluentcms_publishing/views.py
fluentcms_publishing/locale/.gitkeep
fluentcms_publishing/pagetypes/__init__.py
fluentcms_publishing/pagetypes/fluentpage/__init__.py
fluentcms_publishing/pagetypes/fluentpage/admin.py
fluentcms_publishing/pagetypes/fluentpage/models.py
fluentcms_publishing/pagetypes/fluentpage/page_type_plugins.py
fluentcms_publishing/pagetypes/fluentpage/migrations/0001_initial.py
fluentcms_publishing/pagetypes/fluentpage/migrations/__init__.py
fluentcms_publishing/pagetypes/fluentpage/static/fluent_pages/fluentpage/fluent_layouts.js
fluentcms_publishing/pagetypes/fluentpage/templates/admin/fluentpage/change_form.html
fluentcms_publishing/pagetypes/redirectnode/__init__.py
fluentcms_publishing/pagetypes/redirectnode/admin.py
fluentcms_publishing/pagetypes/redirectnode/models.py
fluentcms_publishing/pagetypes/redirectnode/page_type_plugins.py
fluentcms_publishing/pagetypes/redirectnode/migrations/0001_initial.py
fluentcms_publishing/pagetypes/redirectnode/migrations/__init__.py
fluentcms_publishing/static/publishing/publishing.css
fluentcms_publishing/static/publishing/publishing.js
fluentcms_publishing/templates/admin/publishing/_change_list_publishing_column.html
fluentcms_publishing/templates/admin/publishing/publishing_change_form.html
fluentcms_publishing/templates/fluentcms_publishing/parts/breadcrumb.html
fluentcms_publishing/templatetags/__init__.py
fluentcms_publishing/templatetags/publishing_tags.py
fluentcms_publishing/tests/__init__.py
fluentcms_publishing/tests/test_admin.py
fluentcms_publishing/tests/test_middleware.py
fluentcms_publishing/tests/test_models.py
fluentcms_publishing-1.2.7.dist-info/METADATA
fluentcms_publishing-1.2.7.dist-info/RECORD
fluentcms_publishing-1.2.7.dist-info/WHEEL
fluentcms_publishing-1.2.7.dist-info/top_level.txt
