Metadata-Version: 2.1
Name: fluentcms-publishing
Version: 1.2.7
Summary: django-fluent-pages meets django-model-publisher
Home-page: https://github.com/bashu/fluentcms-publishing
Author: Basil Shubin
Author-email: basil.shubin@gmail.com
License: MIT License
Download-URL: https://github.com/bashu/fluentcms-publishing/zipball/master
Platform: UNKNOWN
Classifier: Development Status :: 4 - Beta
Classifier: Environment :: Web Environment
Classifier: Framework :: Django
Classifier: Intended Audience :: Developers
Classifier: License :: OSI Approved :: MIT License
Classifier: Operating System :: OS Independent
Classifier: Programming Language :: Python
Classifier: Programming Language :: Python :: 2
Classifier: Programming Language :: Python :: 2.7
Classifier: Programming Language :: Python :: 3
Classifier: Programming Language :: Python :: 3.4
Classifier: Programming Language :: Python :: 3.6
Classifier: Topic :: Internet :: WWW/HTTP
Classifier: Topic :: Internet :: WWW/HTTP :: Dynamic Content
Classifier: Topic :: Software Development :: Libraries :: Python Modules
Requires: Django (>=1.11)
Requires-Dist: django-model-publisher (>0.1.5)
Requires-Dist: django-model-settings (>0.3)
